ItemResponseCalc/__init__.py
ItemResponseCalc/gamma.py
ItemResponseCalc/gauss.py
ItemResponseCalc/ir_base.py
ItemResponseCalc/ir_display.py
ItemResponseCalc/ir_display_format.py
ItemResponseCalc/ir_global.py
ItemResponseCalc/ir_graded_response_prob.py
ItemResponseCalc/ir_group.py
ItemResponseCalc/ir_latent.py
ItemResponseCalc/ir_logging.py
ItemResponseCalc/ir_model.py
ItemResponseCalc/ir_source.py
ItemResponseCalc/ir_thresholds.py
ItemResponseCalc/item_response_data.py
ItemResponseCalc/item_trait_selector.py
ItemResponseCalc/run_irt.py
ItemResponseCalc/student.py
ItemResponseCalc/wishart.py
ItemResponseCalc-1.0.0.dist-info/LICENSE.txt
ItemResponseCalc-1.0.0.dist-info/METADATA
ItemResponseCalc-1.0.0.dist-info/WHEEL
ItemResponseCalc-1.0.0.dist-info/top_level.txt
ItemResponseCalc-1.0.0.dist-info/RECORD
