Metadata-Version: 2.1
Name: ItemResponseCalc
Version: 1.0.0
Summary: Statistical Analysis of Questionnaire Response Data
Author: Arne Leijon
Author-email: leijon@kth.se
License: MIT License
Keywords: Questionnaire,Item Response Theory,IRT,Ordinal Ratings,Bayesian
Classifier: Development Status :: 4 - Beta
Classifier: Programming Language :: Python :: 3.6
Classifier: License :: OSI Approved :: MIT License
Classifier: Operating System :: OS Independent
Classifier: Intended Audience :: Science/Research
Classifier: Topic :: Scientific/Engineering :: Information Analysis
Classifier: Topic :: Multimedia :: Sound/Audio
Requires-Python: >=3.9
License-File: LICENSE.txt
Requires-Dist: numpy >=1.17
Requires-Dist: scipy >=1.7
Requires-Dist: matplotlib
Requires-Dist: samppy >=1.2.2
Requires-Dist: pandas >=2.0
Requires-Dist: openpyxl >=3.0
